psr/warehouse/__init__.py
psr/warehouse/client.py
psr/warehouse/py.typed
psr_warehouse-0.1.0.dist-info/METADATA
psr_warehouse-0.1.0.dist-info/WHEEL
psr_warehouse-0.1.0.dist-info/licenses/LICENSE
psr_warehouse-0.1.0.dist-info/RECORD
