Metadata-Version: 2.4
Name: psr-warehouse
Version: 0.1.0
Summary: Add your description here
License-File: LICENSE
Requires-Python: >=3.13
Requires-Dist: pandas>=2.3.0
Requires-Dist: psycopg[binary]>=3.2.9
Requires-Dist: sqlalchemy>=2.0.41
